pytz_deprecation_shim/__init__.py
pytz_deprecation_shim/_common.py
pytz_deprecation_shim/_compat.py
pytz_deprecation_shim/_compat_py2.py
pytz_deprecation_shim/_compat_py3.py
pytz_deprecation_shim/_exceptions.py
pytz_deprecation_shim/_impl.py
pytz_deprecation_shim/helpers.py
pytz_deprecation_shim-0.1.0.dist-info/LICENSE
pytz_deprecation_shim-0.1.0.dist-info/LICENSE_APACHE
pytz_deprecation_shim-0.1.0.dist-info/METADATA
pytz_deprecation_shim-0.1.0.dist-info/WHEEL
pytz_deprecation_shim-0.1.0.dist-info/top_level.txt
pytz_deprecation_shim-0.1.0.dist-info/RECORD
