Metadata-Version: 2.1
Name: pytz_deprecation_shim
Version: 0.1.0
Summary: Shims to make deprecation of pytz easier
Home-page: https://github.com/pganssle/pytz-deprecation-shim
Author: Paul Ganssle
Author-email: paul@ganssle.io
License: Apache-2.0
Project-URL: Bug Reports, https://github.com/pganssle/python-deprecation-shim
Project-URL: Source, https://github.com/pganssle/python-deprecation-shim
Project-URL: Documentation, https://python-deprecation-shim.readthedocs.io
Platform: UNKNOWN
Classifier: Development Status :: 4 - Beta
Classifier: Intended Audience :: Developers
Classifier: License :: OSI Approved :: Apache Software License
Classifier: Programming Language :: Python :: 2
Classifier: Programming Language :: Python :: 2.7
Classifier: Programming Language :: Python :: 3
Classifier: Programming Language :: Python :: 3.6
Classifier: Programming Language :: Python :: 3.7
Classifier: Programming Language :: Python :: 3.8
Classifier: Programming Language :: Python :: 3.9
Requires-Python: !=3.0.*,!=3.1.*,!=3.2.*,!=3.3.*,!=3.4.*,!=3.5.*,>=2.7
